rehome/__init__.py
rehome/cli.py
rehome/log_utils.py
rehome/new_home.py
rehome/py.typed
rehome-0.0.1.dist-info/LICENSE
rehome-0.0.1.dist-info/METADATA
rehome-0.0.1.dist-info/WHEEL
rehome-0.0.1.dist-info/entry_points.txt
rehome-0.0.1.dist-info/top_level.txt
rehome-0.0.1.dist-info/RECORD
